{
  "required": true,
  "package": "xyz.wagyourtail.jsmacros.client.mixins",
  "compatibilityLevel": "JAVA_17",
  "client": [
    "xyz.wagyourtail.jsmacros.client.mixin.access.MixinAbstractFurnaceScreenHandler",
    "xyz.wagyourtail.jsmacros.client.mixin.access.MixinAbstractHorseEntity",
    "xyz.wagyourtail.jsmacros.client.mixin.access.MixinAbstractPiglinEntity",
    "xyz.wagyourtail.jsmacros.client.mixin.access.MixinAdvancementManager",
    "xyz.wagyourtail.jsmacros.client.mixin.access.MixinAdvancementProgress",
    "xyz.wagyourtail.jsmacros.client.mixin.access.MixinAllayEntity",
    "xyz.wagyourtail.jsmacros.client.mixin.access.MixinAnvilScreen",
    "xyz.wagyourtail.jsmacros.client.mixin.access.MixinBeaconScreen",
    "xyz.wagyourtail.jsmacros.client.mixin.access.MixinBoatEntity",
    "xyz.wagyourtail.jsmacros.client.mixin.access.MixinBossBarHud",
    "xyz.wagyourtail.jsmacros.client.mixin.access.MixinChatHud",
    "xyz.wagyourtail.jsmacros.client.mixin.access.MixinChunkSelection",
    "xyz.wagyourtail.jsmacros.client.mixin.access.MixinClientAdvancementManager",
    "access.MixinClientPlayerInteractionManager",
    "xyz.wagyourtail.jsmacros.client.mixin.access.MixinClientPlayNetworkHandler",
    "xyz.wagyourtail.jsmacros.client.mixin.access.MixinCreativeInventoryScreen",
    "xyz.wagyourtail.jsmacros.client.mixin.access.MixinCreeperEntity",
    "xyz.wagyourtail.jsmacros.client.mixin.access.MixinCyclingButton",
    "xyz.wagyourtail.jsmacros.client.mixin.access.MixinDisconnectedScreen",
    "xyz.wagyourtail.jsmacros.client.mixin.access.MixinDisplayEntity",
    "xyz.wagyourtail.jsmacros.client.mixin.access.MixinEntity",
    "xyz.wagyourtail.jsmacros.client.mixin.access.MixinEntity2",
    "xyz.wagyourtail.jsmacros.client.mixin.access.MixinFishingBobberEntity",
    "xyz.wagyourtail.jsmacros.client.mixin.access.MixinFontManager",
    "xyz.wagyourtail.jsmacros.client.mixin.access.MixinFontStorage",
    "xyz.wagyourtail.jsmacros.client.mixin.access.MixinFoxEntity",
    "xyz.wagyourtail.jsmacros.client.mixin.access.MixinHandledScreen",
    "xyz.wagyourtail.jsmacros.client.mixin.access.MixinHorseEntity",
    "xyz.wagyourtail.jsmacros.client.mixin.access.MixinHorseScreen",
    "xyz.wagyourtail.jsmacros.client.mixin.access.MixinInteractionEntity",
    "xyz.wagyourtail.jsmacros.client.mixin.access.MixinInteractionEntity2",
    "xyz.wagyourtail.jsmacros.client.mixin.access.MixinItemCooldownEntry",
    "xyz.wagyourtail.jsmacros.client.mixin.access.MixinItemCooldownManager",
    "xyz.wagyourtail.jsmacros.client.mixin.access.MixinLoomScreen",
    "xyz.wagyourtail.jsmacros.client.mixin.access.MixinMerchantEntity",
    "xyz.wagyourtail.jsmacros.client.mixin.access.MixinMerchantScreen",
    "access.MixinMinecraftClient",
    "xyz.wagyourtail.jsmacros.client.mixin.access.MixinOcelotEntity",
    "xyz.wagyourtail.jsmacros.client.mixin.access.MixinPackedIntegerArray",
    "xyz.wagyourtail.jsmacros.client.mixin.access.MixinPalettedContainer",
    "xyz.wagyourtail.jsmacros.client.mixin.access.MixinPalettedContainerData",
    "xyz.wagyourtail.jsmacros.client.mixin.access.MixinPhaseType",
    "xyz.wagyourtail.jsmacros.client.mixin.access.MixinPlayerEntity",
    "xyz.wagyourtail.jsmacros.client.mixin.access.MixinPlayerListHud",
    "xyz.wagyourtail.jsmacros.client.mixin.access.MixinRecipeBookResults",
    "xyz.wagyourtail.jsmacros.client.mixin.access.MixinRecipeBookWidget",
    "xyz.wagyourtail.jsmacros.client.mixin.access.MixinResourcePackManager",
    "xyz.wagyourtail.jsmacros.client.mixin.access.MixinScreen",
    "xyz.wagyourtail.jsmacros.client.mixin.access.MixinShulkerEntity",
    "xyz.wagyourtail.jsmacros.client.mixin.access.MixinSignEditScreen",
    "xyz.wagyourtail.jsmacros.client.mixin.access.MixinSimpleOption",
    "xyz.wagyourtail.jsmacros.client.mixin.access.MixinSpellcastingIllagerEntityHelper",
    "xyz.wagyourtail.jsmacros.client.mixin.access.MixinStatHandler",
    "xyz.wagyourtail.jsmacros.client.mixin.access.MixinStyleSerializer",
    "xyz.wagyourtail.jsmacros.client.mixin.access.MixinTextFieldWidget",
    "xyz.wagyourtail.jsmacros.client.mixin.access.MixinTranslationStorage",
    "xyz.wagyourtail.jsmacros.client.mixin.access.MixinTridentEntity",
    "xyz.wagyourtail.jsmacros.client.mixin.access.MixinTrueTypeFont",
    "xyz.wagyourtail.jsmacros.client.mixin.access.MixinWorldRenderer",
    "events.MixinChatHud",
    "xyz.wagyourtail.jsmacros.client.mixin.events.MixinChatScreen",
    "xyz.wagyourtail.jsmacros.client.mixin.events.MixinClientConnection",
    "events.MixinClientPlayerEntity",
    "xyz.wagyourtail.jsmacros.client.mixin.events.MixinClientPlayerInteractionManager",
    "xyz.wagyourtail.jsmacros.client.mixin.events.MixinClientPlayNetworkHandler",
    "xyz.wagyourtail.jsmacros.client.mixin.events.MixinClientWorld",
    "xyz.wagyourtail.jsmacros.client.mixin.events.MixinCreativeInventoryScreen",
    "xyz.wagyourtail.jsmacros.client.mixin.events.MixinDataTracker",
    "xyz.wagyourtail.jsmacros.client.mixin.events.MixinHandledScreen",
    "xyz.wagyourtail.jsmacros.client.mixin.events.MixinHungerManager",
    "events.MixinKeyboard",
    "xyz.wagyourtail.jsmacros.client.mixin.events.MixinLivingEntity",
    "xyz.wagyourtail.jsmacros.client.mixin.events.MixinMessageHandler",
    "xyz.wagyourtail.jsmacros.client.mixin.events.MixinMinecraftClient",
    "events.MixinMouse",
    "xyz.wagyourtail.jsmacros.client.mixin.events.MixinSoundSystem",
    "xyz.wagyourtail.jsmacros.client.mixin.events.MixinSplashOverlay"
  ],
  "injectors": {
    "defaultRequire": 1
  },
  "mixins": [
    "xyz.wagyourtail.jsmacros.client.mixin.access.MixinBlockPredicatesChecker",
    "xyz.wagyourtail.jsmacros.client.mixin.access.MixinItemEnchantmentsComponent"
  ]
}
