{
    "required": true,
    "package": "xyz.wagyourtail.jsmacros.client.mixins",
    "compatibilityLevel": "JAVA_8",
    "refmap": "jsmacros-common.refmap.json",
    "client": [
        "access.MixinBeaconScreen",
        "access.MixinChatHud",
        "access.MixinClientPlayNetworkHandler",
        "access.MixinEntity",
        "access.MixinExtendedBlockStorage",
        "access.MixinGuiTextField",
        "access.MixinHorseScreen",
        "access.MixinKeyboard",
        "access.MixinMerchantScreen",
        "access.MixinMinecraftClient",
        "access.MixinMouse",
        "access.MixinObjectIntIdentityMap",
        "access.MixinPlayerEntity",
        "access.MixinPlayerListHud",
        "access.MixinResourcePackManager",
        "access.MixinScreen",
        "access.MixinSignEditScreen",
        "access.MixinStatHandler",
        "access.MixinStyle",
        "access.MixinStyleSerializer",
        "access.MixinTranslationStorage",
        "access.MixinVillager",
        "events.MixinBossStatus",
        "events.MixinChatHud",
        "events.MixinClientPlayerEntity",
        "events.MixinClientPlayerInteractionManager",
        "events.MixinClientPlayNetworkHandler",
        "events.MixinClientWorld",
        "events.MixinCreativeInventoryScreen",
        "events.MixinEntityLivingBase",
        "events.MixinHandledScreen",
        "events.MixinHungerManager",
        "events.MixinLivingEntity",
        "events.MixinMinecraftClient",
        "events.MixinScreen",
        "events.MixinSoundSystem"
    ],
    "injectors": {
        "defaultRequire": 1
    },
    "mixins": [
    ]
}
